{"mc":{
	"action":{
		"frameRate":8,
		"labels":[
			{"name":"1","frame":1,"end":7}
			
			],
		"events":[
			
			],
		"frames":[
			
			{
			"res":"shuipao0002",
			"x":-21,
			"y":-63
			},
			{
			"res":"shuipao0004",
			"x":-23,
			"y":-85
			},
			{
			"res":"shuipao0006",
			"x":-25,
			"y":-117
			},
			{
			"res":"shuipao0008",
			"x":-21,
			"y":-105
			},
			{
			"res":"shuipao0010",
			"x":-22,
			"y":-104
			},
			{
			"res":"shuipao0012",
			"x":-24,
			"y":-101
			},
			{
			"res":"shuipao0014",
			"x":-11,
			"y":-94
			}
			]
}},
	"res":{
		"shuipao0006":{"x":1,"y":1,"w":42,"h":74},
		"shuipao0012":{"x":86,"y":1,"w":40,"h":69},
		"shuipao0004":{"x":1,"y":77,"w":38,"h":65},
		"shuipao0002":{"x":41,"y":123,"w":34,"h":32},
		"shuipao0008":{"x":45,"y":1,"w":39,"h":78},
		"shuipao0010":{"x":86,"y":72,"w":41,"h":63},
		"shuipao0014":{"x":41,"y":81,"w":28,"h":40}
	}}